koldar_utils/__init__.py
koldar_utils/version.py
koldar_utils/functions/__init__.py
koldar_utils/functions/decorators.py
koldar_utils/functions/file_helpers.py
koldar_utils/functions/http_helpers.py
koldar_utils/functions/image_helpers.py
koldar_utils/functions/iterator_helpers.py
koldar_utils/functions/logic_helpers.py
koldar_utils/functions/math_helpers.py
koldar_utils/functions/modules.py
koldar_utils/functions/python_helpers.py
koldar_utils/functions/secrets_helper.py
koldar_utils/functions/stacktrace.py
koldar_utils/functions/time.py
koldar_utils/models/AbstractEnum.py
koldar_utils/models/AttrDict.py
koldar_utils/models/__init__.py
koldar_utils/setuptools_toolbox/__init__.py
koldar_utils/setuptools_toolbox/commons.py
koldar_utils/setuptools_toolbox/console_script_setup.py
koldar_utils/setuptools_toolbox/django_project_script_setup.py
koldar_utils/setuptools_toolbox/library_setup.py
koldar_utils/sphinx_toolbox/__init__.py
koldar_utils/sphinx_toolbox/sphinx_helper.py
koldar_utils/tests/TestIteratorHelpers.py
koldar_utils/tests/__init__.py
koldar_utils-2.104.5.dist-info/LICENSE.md
koldar_utils-2.104.5.dist-info/METADATA
koldar_utils-2.104.5.dist-info/WHEEL
koldar_utils-2.104.5.dist-info/top_level.txt
koldar_utils-2.104.5.dist-info/RECORD
