Metadata-Version: 2.1
Name: koldar-utils
Version: 2.104.5
Summary: Some stuff that i used when developing with python. You can use this library pretty much anywhere
Home-page: https://github.com/Koldar/django-koldar-common-apps
Author: Massimo Bono
Author-email: massimobono1@gmail.com
License: MIT
Keywords: utils
Platform: UNKNOWN
Classifier: Programming Language :: Python :: 3
Classifier: Operating System :: OS Independent
Requires-Python: >=3.6
License-File: LICENSE.md
License-File: README.md
License-File: requirements.txt
License-File: setup.py
Requires-Dist: datasize (>=1.0.0)
Requires-Dist: docutils (>=0.17.1)
Requires-Dist: jmespath (>=0.10.0)
Requires-Dist: m2r (>=0.2.1)
Requires-Dist: mistune (>=0.8.4)
Requires-Dist: Pillow (>=8.3.2)
Requires-Dist: semantic-version (>=2.8.5)
Requires-Dist: stringcase (>=1.2.0)
Provides-Extra: docs
Requires-Dist: sphinx ; extra == 'docs'
Requires-Dist: sphinx-rtd-theme ; extra == 'docs'
Requires-Dist: sphinx-autodoc-typehints ; extra == 'docs'
Provides-Extra: test
Requires-Dist: pytest ; extra == 'test'
Requires-Dist: mock ; extra == 'test'
